smartcpp.so
smartcpp-0.2.0.dist-info/LICENCE.md
smartcpp-0.2.0.dist-info/METADATA
smartcpp-0.2.0.dist-info/WHEEL
smartcpp-0.2.0.dist-info/top_level.txt
smartcpp-0.2.0.dist-info/RECORD
