Metadata-Version: 2.1
Name: smartcpp
Version: 0.2.0
Summary: SMARTcpp: a C++ extension of the rainfall-runoff SMART for Python
Home-page: https://github.com/ThibHlln/smartcpp
Author: Thibault Hallouin, Michael Bruen, and Eva Mockler
Author-email: thibault.hallouin@ucdconnect.ie
License: GPLv3
Platform: UNKNOWN
Classifier: Development Status :: 4 - Beta
Classifier: Natural Language :: English
Classifier: Intended Audience :: Science/Research
Classifier: Intended Audience :: Developers
Classifier: Topic :: Scientific/Engineering
Classifier: Operating System :: MacOS
Classifier: Operating System :: Microsoft :: Windows :: Windows 10
Classifier: License :: OSI Approved :: GNU General Public License v3 (GPLv3)
Classifier: Programming Language :: C++
Classifier: Programming Language :: Python :: 2
Classifier: Programming Language :: Python :: 2.7
Classifier: Programming Language :: Python :: 3
Classifier: Programming Language :: Python :: 3.6
Classifier: Programming Language :: Python :: Implementation :: CPython
Requires-Python: >=2.7
Requires-Dist: numpy
